examples/__init__.py
examples/clip_to_puppydb.py
examples/hnsw_search_puppydb.py
examples/knn_search_puppydb.py
pup_py_db-0.1.0.dist-info/licenses/LICENSE
puppydb/__init__.py
puppydb/core.py
puppydb/metadata_store.py
puppydb/search.py
puppydb/utils.py
puppydb/vector_store.py
pup_py_db-0.1.0.dist-info/METADATA
pup_py_db-0.1.0.dist-info/WHEEL
pup_py_db-0.1.0.dist-info/top_level.txt
pup_py_db-0.1.0.dist-info/RECORD
