Metadata-Version: 2.4
Name: pup-py-db
Version: 0.1.0
Summary: An experimental vector database built from scratch with flat files, LMDB, and HNSW.
Home-page: https://github.com/sarabesh/PuppyDB
Author: Sarabesh
License: MIT
Project-URL: Bug Tracker, https://github.com/sarabesh/PuppyDB/issues
Classifier: Development Status :: 3 - Alpha
Classifier: License :: OSI Approved :: MIT License
Classifier: Programming Language :: Python :: 3
Classifier: Programming Language :: Python :: 3.9
Classifier: Programming Language :: Python :: 3.10
Classifier: Programming Language :: Python :: 3.11
Classifier: Operating System :: OS Independent
Classifier: Intended Audience :: Developers
Classifier: Topic :: Database
Classifier: Topic :: Scientific/Engineering :: Artificial Intelligence
Requires-Python: >=3.9
License-File: LICENSE
Requires-Dist: numpy
Requires-Dist: lmdb
Dynamic: author
Dynamic: classifier
Dynamic: home-page
Dynamic: license
Dynamic: license-file
Dynamic: project-url
Dynamic: requires-dist
Dynamic: requires-python
Dynamic: summary
